rugbypy/__init__.py
rugbypy/_modidx.py
rugbypy/competition.py
rugbypy/match.py
rugbypy/player.py
rugbypy/team.py
rugbypy/venue.py
rugbypy-3.0.0.dist-info/licenses/LICENSE
rugbypy-3.0.0.dist-info/METADATA
rugbypy-3.0.0.dist-info/WHEEL
rugbypy-3.0.0.dist-info/entry_points.txt
rugbypy-3.0.0.dist-info/top_level.txt
rugbypy-3.0.0.dist-info/RECORD
