Metadata-Version: 2.4
Name: rugbypy
Version: 3.0.0
Summary: Repository for rugby data analytics
Home-page: https://github.com/seanyboi/rugbypy
Author: seanyboi
Author-email: oconnorjamessean@gmail.com
License: Apache Software License 2.0
Keywords: nbdev jupyter notebook python rugby sports analytics
Classifier: Development Status :: 4 - Beta
Classifier: Intended Audience :: Developers
Classifier: Natural Language :: English
Classifier: Programming Language :: Python :: 3.11
Classifier: Programming Language :: Python :: 3.12
Classifier: License :: OSI Approved :: Apache Software License
Requires-Python: >=3.11
License-File: LICENSE
Requires-Dist: fastcore
Requires-Dist: pandas==2.3.3
Requires-Dist: pyarrow==19.0.0
Requires-Dist: requests
Provides-Extra: dev
Requires-Dist: black; extra == "dev"
Dynamic: author
Dynamic: author-email
Dynamic: classifier
Dynamic: description
Dynamic: description-content-type
Dynamic: home-page
Dynamic: keywords
Dynamic: license
Dynamic: license-file
Dynamic: provides-extra
Dynamic: requires-dist
Dynamic: requires-python
Dynamic: summary
